CMakeLists.txt
MANIFEST.in
README.md
VERSION_NUMBER
setup.py
demo/CMakeLists.txt
demo/README.md
demo/build.sh
demo/dataloader.hpp
demo/image_classification_demo.cc
demo/object_detection.hpp
demo/object_detection_demo.cc
demo/object_detection_stream_demo.cc
demo/object_detection_video_demo.cc
demo/pose_estimation.hpp
demo/pose_estimation_demo.cc
demo/pose_tracker_stream_demo.cc
demo/utils/cv_helper.hpp
demo/utils/json.hpp
demo/utils/json_helper.hpp
demo/utils/win_getopt/mb/getopt.cc
demo/utils/win_getopt/mb/include/getopt.h
demo/utils/win_getopt/mb/include/unistd.h
demo/utils/win_getopt/wide/getopt.cc
demo/utils/win_getopt/wide/include/getopt.h
include/task/vision/image_classification_task.h
include/task/vision/image_classification_types.h
include/task/vision/object_detection_task.h
include/task/vision/object_detection_types.h
include/task/vision/pose_estimation_task.h
include/task/vision/pose_estimation_types.h
include/utils/time.h
include/utils/utils.h
pybind11/.appveyor.yml
pybind11/.clang-format
pybind11/.clang-tidy
pybind11/.cmake-format.yaml
pybind11/.codespell-ignore-lines
pybind11/.git
pybind11/.gitattributes
pybind11/.gitignore
pybind11/.pre-commit-config.yaml
pybind11/.readthedocs.yml
pybind11/CMakeLists.txt
pybind11/LICENSE
pybind11/MANIFEST.in
pybind11/README.rst
pybind11/SECURITY.md
pybind11/noxfile.py
pybind11/pyproject.toml
pybind11/setup.cfg
pybind11/setup.py
pybind11/.github/CODEOWNERS
pybind11/.github/CONTRIBUTING.md
pybind11/.github/dependabot.yml
pybind11/.github/labeler.yml
pybind11/.github/labeler_merged.yml
pybind11/.github/pull_request_template.md
pybind11/.github/ISSUE_TEMPLATE/bug-report.yml
pybind11/.github/ISSUE_TEMPLATE/config.yml
pybind11/.github/matchers/pylint.json
pybind11/.github/workflows/ci.yml
pybind11/.github/workflows/configure.yml
pybind11/.github/workflows/format.yml
pybind11/.github/workflows/labeler.yml
pybind11/.github/workflows/pip.yml
pybind11/.github/workflows/upstream.yml
pybind11/docs/Doxyfile
pybind11/docs/Makefile
python/bianbuai.egg-info/PKG-INFO
python/bianbuai.egg-info/SOURCES.txt
python/bianbuai.egg-info/dependency_links.txt
python/bianbuai.egg-info/not-zip-safe
python/bianbuai.egg-info/top_level.txt
